[{"Plan": {"Node Type": "Aggregate", "Strategy": "Plain", "Partial Mode": "Finalize", "Parallel Aware": false, "Async Capable": false, "Startup Cost": 247788.53, "Total Cost": 247788.54, "Plan Rows": 1, "Plan Width": 32, "Actual Rows": 1, "Actual Loops": 1, "Plans": [{"Node Type": "Gather", "Parent Relationship": "Outer", "Parallel Aware": false, "Async Capable": false, "Startup Cost": 247788.01, "Total Cost": 247788.52, "Plan Rows": 5, "Plan Width": 32, "Actual Rows": 6, "Actual Loops": 1, "Workers Planned": 5, "Workers Launched": 5, "Single Copy": false, "Plans": [{"Node Type": "Aggregate", "Strategy": "Plain", "Partial Mode": "Partial", "Parent Relationship": "Outer", "Parallel Aware": false, "Async Capable": false, "Startup Cost": 246788.01, "Total Cost": 246788.02, "Plan Rows": 1, "Plan Width": 32, "Actual Rows": 1, "Actual Loops": 6, "Workers": [], "Plans": [{"Node Type": "Hash Join", "Parent Relationship": "Outer", "Parallel Aware": false, "Async Capable": false, "Join Type": "Inner", "Startup Cost": 31923.17, "Total Cost": 246773.25, "Plan Rows": 5905, "Plan Width": 17, "Actual Rows": 112, "Actual Loops": 6, "Inner Unique": true, "Hash Cond": "(mi.info_type_id = it.id)", "Workers": [], "Plans": [{"Node Type": "Nested Loop", "Parent Relationship": "Outer", "Parallel Aware": false, "Async Capable": false, "Join Type": "Inner", "Startup Cost": 31919.62, "Total Cost": 246753.63, "Plan Rows": 5905, "Plan Width": 21, "Actual Rows": 112, "Actual Loops": 6, "Inner Unique": true, "Workers": [], "Plans": [{"Node Type": "Hash Join", "Parent Relationship": "Outer", "Parallel Aware": true, "Async Capable": false, "Join Type": "Inner", "Startup Cost": 31919.19, "Total Cost": 240728.03, "Plan Rows": 8520, "Plan Width": 12, "Actual Rows": 115, "Actual Loops": 6, "Inner Unique": false, "Hash Cond": "(mi.movie_id = mc.movie_id)", "Workers": [], "Plans": [{"Node Type": "Seq Scan", "Parent Relationship": "Outer", "Parallel Aware": true, "Async Capable": false, "Relation Name": "movie_info", "Alias": "mi", "Startup Cost": 0.03, "Total Cost": 206156.62, "Plan Rows": 139987, "Plan Width": 8, "Actual Rows": 117779, "Actual Loops": 6, "Filter": "((info)::text = ANY ('{Sweden,Norway,Germany,Denmark,Swedish,Denish,Norwegian,German,USA,American}'::text[]))", "Rows Removed by Filter": 2354841, "Workers": []}, {"Node Type": "Hash", "Parent Relationship": "Inner", "Parallel Aware": true, "Async Capable": false, "Startup Cost": 31747.27, "Total Cost": 31747.27, "Plan Rows": 13752, "Plan Width": 4, "Actual Rows": 133, "Actual Loops": 6, "Hash Buckets": 65536, "Original Hash Buckets": 65536, "Hash Batches": 1, "Original Hash Batches": 1, "Peak Memory Usage": 704, "Workers": [], "Plans": [{"Node Type": "Hash Join", "Parent Relationship": "Outer", "Parallel Aware": false, "Async Capable": false, "Join Type": "Inner", "Startup Cost": 1.06, "Total Cost": 31747.27, "Plan Rows": 13752, "Plan Width": 4, "Actual Rows": 133, "Actual Loops": 6, "Inner Unique": true, "Hash Cond": "(mc.company_type_id = ct.id)", "Workers": [], "Plans": [{"Node Type": "Seq Scan", "Parent Relationship": "Outer", "Parallel Aware": true, "Async Capable": false, "Relation Name": "movie_companies", "Alias": "mc", "Startup Cost": 0.0, "Total Cost": 31448.82, "Plan Rows": 55009, "Plan Width": 8, "Actual Rows": 49271, "Actual Loops": 6, "Filter": "(((note)::text !~~ '%(TV)%'::text) AND ((note)::text ~~ '%(USA)%'::text))", "Rows Removed by Filter": 385584, "Workers": []}, {"Node Type": "Hash", "Parent Relationship": "Inner", "Parallel Aware": false, "Async Capable": false, "Startup Cost": 1.05, "Total Cost": 1.05, "Plan Rows": 1, "Plan Width": 4, "Actual Rows": 1, "Actual Loops": 6, "Hash Buckets": 1024, "Original Hash Buckets": 1024, "Hash Batches": 1, "Original Hash Batches": 1, "Peak Memory Usage": 9, "Workers": [], "Plans": [{"Node Type": "Seq Scan", "Parent Relationship": "Outer", "Parallel Aware": false, "Async Capable": false, "Relation Name": "company_type", "Alias": "ct", "Startup Cost": 0.0, "Total Cost": 1.05, "Plan Rows": 1, "Plan Width": 4, "Actual Rows": 1, "Actual Loops": 6, "Filter": "((kind)::text = 'production companies'::text)", "Rows Removed by Filter": 3, "Workers": []}]}]}]}]}, {"Node Type": "Index Scan", "Parent Relationship": "Inner", "Parallel Aware": false, "Async Capable": false, "Scan Direction": "Forward", "Index Name": "title_pkey", "Relation Name": "title", "Alias": "t", "Startup Cost": 0.43, "Total Cost": 0.71, "Plan Rows": 1, "Plan Width": 21, "Actual Rows": 1, "Actual Loops": 691, "Index Cond": "(id = mi.movie_id)", "Rows Removed by Index Recheck": 0, "Filter": "(production_year > 1990)", "Rows Removed by Filter": 0, "Workers": []}]}, {"Node Type": "Hash", "Parent Relationship": "Inner", "Parallel Aware": false, "Async Capable": false, "Startup Cost": 2.13, "Total Cost": 2.13, "Plan Rows": 113, "Plan Width": 4, "Actual Rows": 113, "Actual Loops": 6, "Hash Buckets": 1024, "Original Hash Buckets": 1024, "Hash Batches": 1, "Original Hash Batches": 1, "Peak Memory Usage": 12, "Workers": [], "Plans": [{"Node Type": "Seq Scan", "Parent Relationship": "Outer", "Parallel Aware": false, "Async Capable": false, "Relation Name": "info_type", "Alias": "it", "Startup Cost": 0.0, "Total Cost": 2.13, "Plan Rows": 113, "Plan Width": 4, "Actual Rows": 113, "Actual Loops": 6, "Workers": []}]}]}]}]}]}, "Planning Time": 3.8, "Triggers": [], "Execution Time": 565.358}, {"Plan": {"Node Type": "Aggregate", "Strategy": "Plain", "Partial Mode": "Finalize", "Parallel Aware": false, "Async Capable": false, "Startup Cost": 247775.25, "Total Cost": 247775.26, "Plan Rows": 1, "Plan Width": 32, "Actual Rows": 1, "Actual Loops": 1, "Plans": [{"Node Type": "Gather", "Parent Relationship": "Outer", "Parallel Aware": false, "Async Capable": false, "Startup Cost": 247774.72, "Total Cost": 247775.23, "Plan Rows": 50.0, "Plan Width": 32, "Actual Rows": 6, "Actual Loops": 1, "Workers Planned": 5, "Workers Launched": 5, "Single Copy": false, "Plans": [{"Node Type": "Aggregate", "Strategy": "Plain", "Partial Mode": "Partial", "Parent Relationship": "Outer", "Parallel Aware": false, "Async Capable": false, "Startup Cost": 246774.72, "Total Cost": 246774.73, "Plan Rows": 1, "Plan Width": 32, "Actual Rows": 1, "Actual Loops": 6, "Workers": [], "Plans": [{"Node Type": "Hash Join", "Parent Relationship": "Outer", "Parallel Aware": false, "Async Capable": false, "Join Type": "Inner", "Startup Cost": 31923.17, "Total Cost": 246773.25, "Plan Rows": 5900.0, "Plan Width": 17, "Actual Rows": 112, "Actual Loops": 6, "Inner Unique": true, "Hash Cond": "(mi.info_type_id = it.id)", "Workers": [], "Plans": [{"Node Type": "Nested Loop", "Parent Relationship": "Outer", "Parallel Aware": false, "Async Capable": false, "Join Type": "Inner", "Startup Cost": 31919.62, "Total Cost": 246753.63, "Plan Rows": 5905, "Plan Width": 21, "Actual Rows": 112, "Actual Loops": 6, "Inner Unique": true, "Workers": [], "Plans": [{"Node Type": "Hash Join", "Parent Relationship": "Outer", "Parallel Aware": true, "Async Capable": false, "Join Type": "Inner", "Startup Cost": 31919.19, "Total Cost": 240728.03, "Plan Rows": 8520, "Plan Width": 12, "Actual Rows": 115, "Actual Loops": 6, "Inner Unique": false, "Hash Cond": "(mi.movie_id = mc.movie_id)", "Workers": [], "Plans": [{"Node Type": "Seq Scan", "Parent Relationship": "Outer", "Parallel Aware": true, "Async Capable": false, "Relation Name": "movie_info", "Alias": "mi", "Startup Cost": 0.03, "Total Cost": 206156.62, "Plan Rows": 139987, "Plan Width": 8, "Actual Rows": 117779, "Actual Loops": 6, "Filter": "((info)::text = ANY ('{Sweden,Norway,Germany,Denmark,Swedish,Denish,Norwegian,German,USA,American}'::text[]))", "Rows Removed by Filter": 2354841, "Workers": []}, {"Node Type": "Hash", "Parent Relationship": "Inner", "Parallel Aware": true, "Async Capable": false, "Startup Cost": 31747.27, "Total Cost": 31747.27, "Plan Rows": 13752, "Plan Width": 4, "Actual Rows": 133, "Actual Loops": 6, "Hash Buckets": 65536, "Original Hash Buckets": 65536, "Hash Batches": 1, "Original Hash Batches": 1, "Peak Memory Usage": 704, "Workers": [], "Plans": [{"Node Type": "Hash Join", "Parent Relationship": "Outer", "Parallel Aware": false, "Async Capable": false, "Join Type": "Inner", "Startup Cost": 1.06, "Total Cost": 31747.27, "Plan Rows": 13752, "Plan Width": 4, "Actual Rows": 133, "Actual Loops": 6, "Inner Unique": true, "Hash Cond": "(mc.company_type_id = ct.id)", "Workers": [], "Plans": [{"Node Type": "Seq Scan", "Parent Relationship": "Outer", "Parallel Aware": true, "Async Capable": false, "Relation Name": "movie_companies", "Alias": "mc", "Startup Cost": 0.0, "Total Cost": 31448.82, "Plan Rows": 55009, "Plan Width": 8, "Actual Rows": 49271, "Actual Loops": 6, "Filter": "(((note)::text !~~ '%(TV)%'::text) AND ((note)::text ~~ '%(USA)%'::text))", "Rows Removed by Filter": 385584, "Workers": []}, {"Node Type": "Hash", "Parent Relationship": "Inner", "Parallel Aware": false, "Async Capable": false, "Startup Cost": 1.05, "Total Cost": 1.05, "Plan Rows": 1, "Plan Width": 4, "Actual Rows": 1, "Actual Loops": 6, "Hash Buckets": 1024, "Original Hash Buckets": 1024, "Hash Batches": 1, "Original Hash Batches": 1, "Peak Memory Usage": 9, "Workers": [], "Plans": [{"Node Type": "Seq Scan", "Parent Relationship": "Outer", "Parallel Aware": false, "Async Capable": false, "Relation Name": "company_type", "Alias": "ct", "Startup Cost": 0.0, "Total Cost": 1.05, "Plan Rows": 1, "Plan Width": 4, "Actual Rows": 1, "Actual Loops": 6, "Filter": "((kind)::text = 'production companies'::text)", "Rows Removed by Filter": 3, "Workers": []}]}]}]}]}, {"Node Type": "Index Scan", "Parent Relationship": "Inner", "Parallel Aware": false, "Async Capable": false, "Scan Direction": "Forward", "Index Name": "title_pkey", "Relation Name": "title", "Alias": "t", "Startup Cost": 0.43, "Total Cost": 0.71, "Plan Rows": 1, "Plan Width": 21, "Actual Rows": 1, "Actual Loops": 691, "Index Cond": "(id = mi.movie_id)", "Rows Removed by Index Recheck": 0, "Filter": "(production_year > 1990)", "Rows Removed by Filter": 0, "Workers": []}]}, {"Node Type": "Hash", "Parent Relationship": "Inner", "Parallel Aware": false, "Async Capable": false, "Startup Cost": 2.13, "Total Cost": 2.13, "Plan Rows": 113, "Plan Width": 4, "Actual Rows": 113, "Actual Loops": 6, "Hash Buckets": 1024, "Original Hash Buckets": 1024, "Hash Batches": 1, "Original Hash Batches": 1, "Peak Memory Usage": 12, "Workers": [], "Plans": [{"Node Type": "Seq Scan", "Parent Relationship": "Outer", "Parallel Aware": false, "Async Capable": false, "Relation Name": "info_type", "Alias": "it", "Startup Cost": 0.0, "Total Cost": 2.13, "Plan Rows": 113, "Plan Width": 4, "Actual Rows": 113, "Actual Loops": 6, "Workers": []}]}]}]}]}]}, "Planning Time": 3.645, "Triggers": [], "Execution Time": 560.293}, {"Plan": {"Node Type": "Aggregate", "Strategy": "Plain", "Partial Mode": "Finalize", "Parallel Aware": false, "Async Capable": false, "Startup Cost": 242372.61, "Total Cost": 242372.62, "Plan Rows": 1, "Plan Width": 32, "Actual Rows": 1, "Actual Loops": 1, "Plans": [{"Node Type": "Gather", "Parent Relationship": "Outer", "Parallel Aware": false, "Async Capable": false, "Startup Cost": 242372.09, "Total Cost": 242372.6, "Plan Rows": 5, "Plan Width": 32, "Actual Rows": 6, "Actual Loops": 1, "Workers Planned": 5, "Workers Launched": 5, "Single Copy": false, "Plans": [{"Node Type": "Aggregate", "Strategy": "Plain", "Partial Mode": "Partial", "Parent Relationship": "Outer", "Parallel Aware": false, "Async Capable": false, "Startup Cost": 241372.09, "Total Cost": 241372.1, "Plan Rows": 1, "Plan Width": 32, "Actual Rows": 1, "Actual Loops": 6, "Workers": [], "Plans": [{"Node Type": "Nested Loop", "Parent Relationship": "Outer", "Parallel Aware": false, "Async Capable": false, "Join Type": "Inner", "Startup Cost": 31923.17, "Total Cost": 241357.33, "Plan Rows": 5905, "Plan Width": 17, "Actual Rows": 112, "Actual Loops": 6, "Inner Unique": true, "Workers": [], "Plans": [{"Node Type": "Hash Join", "Parent Relationship": "Outer", "Parallel Aware": false, "Async Capable": false, "Join Type": "Inner", "Startup Cost": 31922.74, "Total Cost": 240754.77, "Plan Rows": 8520.0, "Plan Width": 8, "Actual Rows": 115, "Actual Loops": 6, "Inner Unique": true, "Hash Cond": "(mi.info_type_id = it.id)", "Workers": [], "Plans": [{"Node Type": "Hash Join", "Parent Relationship": "Outer", "Parallel Aware": true, "Async Capable": false, "Join Type": "Inner", "Startup Cost": 31919.19, "Total Cost": 240728.03, "Plan Rows": 8520, "Plan Width": 12, "Actual Rows": 115, "Actual Loops": 6, "Inner Unique": false, "Hash Cond": "(mi.movie_id = mc.movie_id)", "Workers": [], "Plans": [{"Node Type": "Seq Scan", "Parent Relationship": "Outer", "Parallel Aware": true, "Async Capable": false, "Relation Name": "movie_info", "Alias": "mi", "Startup Cost": 0.03, "Total Cost": 206156.62, "Plan Rows": 139987, "Plan Width": 8, "Actual Rows": 117779, "Actual Loops": 6, "Filter": "((info)::text = ANY ('{Sweden,Norway,Germany,Denmark,Swedish,Denish,Norwegian,German,USA,American}'::text[]))", "Rows Removed by Filter": 2354841, "Workers": []}, {"Node Type": "Hash", "Parent Relationship": "Inner", "Parallel Aware": true, "Async Capable": false, "Startup Cost": 31747.27, "Total Cost": 31747.27, "Plan Rows": 13752, "Plan Width": 4, "Actual Rows": 133, "Actual Loops": 6, "Hash Buckets": 65536, "Original Hash Buckets": 65536, "Hash Batches": 1, "Original Hash Batches": 1, "Peak Memory Usage": 704, "Workers": [], "Plans": [{"Node Type": "Hash Join", "Parent Relationship": "Outer", "Parallel Aware": false, "Async Capable": false, "Join Type": "Inner", "Startup Cost": 1.06, "Total Cost": 31747.27, "Plan Rows": 13752, "Plan Width": 4, "Actual Rows": 133, "Actual Loops": 6, "Inner Unique": true, "Hash Cond": "(mc.company_type_id = ct.id)", "Workers": [], "Plans": [{"Node Type": "Seq Scan", "Parent Relationship": "Outer", "Parallel Aware": true, "Async Capable": false, "Relation Name": "movie_companies", "Alias": "mc", "Startup Cost": 0.0, "Total Cost": 31448.82, "Plan Rows": 55009, "Plan Width": 8, "Actual Rows": 49271, "Actual Loops": 6, "Filter": "(((note)::text !~~ '%(TV)%'::text) AND ((note)::text ~~ '%(USA)%'::text))", "Rows Removed by Filter": 385584, "Workers": []}, {"Node Type": "Hash", "Parent Relationship": "Inner", "Parallel Aware": false, "Async Capable": false, "Startup Cost": 1.05, "Total Cost": 1.05, "Plan Rows": 1, "Plan Width": 4, "Actual Rows": 1, "Actual Loops": 6, "Hash Buckets": 1024, "Original Hash Buckets": 1024, "Hash Batches": 1, "Original Hash Batches": 1, "Peak Memory Usage": 9, "Workers": [], "Plans": [{"Node Type": "Seq Scan", "Parent Relationship": "Outer", "Parallel Aware": false, "Async Capable": false, "Relation Name": "company_type", "Alias": "ct", "Startup Cost": 0.0, "Total Cost": 1.05, "Plan Rows": 1, "Plan Width": 4, "Actual Rows": 1, "Actual Loops": 6, "Filter": "((kind)::text = 'production companies'::text)", "Rows Removed by Filter": 3, "Workers": []}]}]}]}]}, {"Node Type": "Hash", "Parent Relationship": "Inner", "Parallel Aware": false, "Async Capable": false, "Startup Cost": 2.13, "Total Cost": 2.13, "Plan Rows": 113, "Plan Width": 4, "Actual Rows": 113, "Actual Loops": 6, "Hash Buckets": 1024, "Original Hash Buckets": 1024, "Hash Batches": 1, "Original Hash Batches": 1, "Peak Memory Usage": 12, "Workers": [], "Plans": [{"Node Type": "Seq Scan", "Parent Relationship": "Outer", "Parallel Aware": false, "Async Capable": false, "Relation Name": "info_type", "Alias": "it", "Startup Cost": 0.0, "Total Cost": 2.13, "Plan Rows": 113, "Plan Width": 4, "Actual Rows": 113, "Actual Loops": 6, "Workers": []}]}]}, {"Node Type": "Index Scan", "Parent Relationship": "Inner", "Parallel Aware": false, "Async Capable": false, "Scan Direction": "Forward", "Index Name": "title_pkey", "Relation Name": "title", "Alias": "t", "Startup Cost": 0.43, "Total Cost": 0.71, "Plan Rows": 1, "Plan Width": 21, "Actual Rows": 1, "Actual Loops": 691, "Index Cond": "(id = mi.movie_id)", "Rows Removed by Index Recheck": 0, "Filter": "(production_year > 1990)", "Rows Removed by Filter": 0, "Workers": []}]}]}]}]}, "Planning Time": 3.46, "Triggers": [], "Execution Time": 560.823}, {"Plan": {"Node Type": "Aggregate", "Strategy": "Plain", "Partial Mode": "Finalize", "Parallel Aware": false, "Async Capable": false, "Startup Cost": 248153.7, "Total Cost": 248153.71, "Plan Rows": 1, "Plan Width": 32, "Actual Rows": 1, "Actual Loops": 1, "Plans": [{"Node Type": "Gather", "Parent Relationship": "Outer", "Parallel Aware": false, "Async Capable": false, "Startup Cost": 248153.18, "Total Cost": 248153.69, "Plan Rows": 5, "Plan Width": 32, "Actual Rows": 6, "Actual Loops": 1, "Workers Planned": 5, "Workers Launched": 5, "Single Copy": false, "Plans": [{"Node Type": "Aggregate", "Strategy": "Plain", "Partial Mode": "Partial", "Parent Relationship": "Outer", "Parallel Aware": false, "Async Capable": false, "Startup Cost": 247153.18, "Total Cost": 247153.19, "Plan Rows": 1, "Plan Width": 32, "Actual Rows": 1, "Actual Loops": 6, "Workers": [], "Plans": [{"Node Type": "Nested Loop", "Parent Relationship": "Outer", "Parallel Aware": false, "Async Capable": false, "Join Type": "Inner", "Startup Cost": 31923.17, "Total Cost": 247138.42, "Plan Rows": 5905, "Plan Width": 17, "Actual Rows": 112, "Actual Loops": 6, "Inner Unique": true, "Workers": [], "Plans": [{"Node Type": "Hash Join", "Parent Relationship": "Outer", "Parallel Aware": true, "Async Capable": false, "Join Type": "Inner", "Startup Cost": 31922.74, "Total Cost": 241112.82, "Plan Rows": 8520, "Plan Width": 8, "Actual Rows": 115, "Actual Loops": 6, "Inner Unique": false, "Hash Cond": "(mi.movie_id = mc.movie_id)", "Workers": [], "Plans": [{"Node Type": "Hash Join", "Parent Relationship": "Outer", "Parallel Aware": false, "Async Capable": false, "Join Type": "Inner", "Startup Cost": 3.57, "Total Cost": 206541.41, "Plan Rows": 139987, "Plan Width": 4, "Actual Rows": 117779, "Actual Loops": 6, "Inner Unique": true, "Hash Cond": "(mi.info_type_id = it.id)", "Workers": [], "Plans": [{"Node Type": "Seq Scan", "Parent Relationship": "Outer", "Parallel Aware": true, "Async Capable": false, "Relation Name": "movie_info", "Alias": "mi", "Startup Cost": 0.03, "Total Cost": 206156.62, "Plan Rows": 139987, "Plan Width": 8, "Actual Rows": 117779, "Actual Loops": 6, "Filter": "((info)::text = ANY ('{Sweden,Norway,Germany,Denmark,Swedish,Denish,Norwegian,German,USA,American}'::text[]))", "Rows Removed by Filter": 2354841, "Workers": []}, {"Node Type": "Hash", "Parent Relationship": "Inner", "Parallel Aware": false, "Async Capable": false, "Startup Cost": 2.13, "Total Cost": 2.13, "Plan Rows": 113, "Plan Width": 4, "Actual Rows": 113, "Actual Loops": 6, "Hash Buckets": 1024, "Original Hash Buckets": 1024, "Hash Batches": 1, "Original Hash Batches": 1, "Peak Memory Usage": 12, "Workers": [], "Plans": [{"Node Type": "Seq Scan", "Parent Relationship": "Outer", "Parallel Aware": false, "Async Capable": false, "Relation Name": "info_type", "Alias": "it", "Startup Cost": 0.0, "Total Cost": 2.13, "Plan Rows": 113, "Plan Width": 4, "Actual Rows": 113, "Actual Loops": 6, "Workers": []}]}]}, {"Node Type": "Hash", "Parent Relationship": "Inner", "Parallel Aware": true, "Async Capable": false, "Startup Cost": 31747.27, "Total Cost": 31747.27, "Plan Rows": 13752, "Plan Width": 4, "Actual Rows": 133, "Actual Loops": 6, "Hash Buckets": 65536, "Original Hash Buckets": 65536, "Hash Batches": 1, "Original Hash Batches": 1, "Peak Memory Usage": 704, "Workers": [], "Plans": [{"Node Type": "Hash Join", "Parent Relationship": "Outer", "Parallel Aware": false, "Async Capable": false, "Join Type": "Inner", "Startup Cost": 1.06, "Total Cost": 31747.27, "Plan Rows": 13752, "Plan Width": 4, "Actual Rows": 133, "Actual Loops": 6, "Inner Unique": true, "Hash Cond": "(mc.company_type_id = ct.id)", "Workers": [], "Plans": [{"Node Type": "Seq Scan", "Parent Relationship": "Outer", "Parallel Aware": true, "Async Capable": false, "Relation Name": "movie_companies", "Alias": "mc", "Startup Cost": 0.0, "Total Cost": 31448.82, "Plan Rows": 55009, "Plan Width": 8, "Actual Rows": 49271, "Actual Loops": 6, "Filter": "(((note)::text !~~ '%(TV)%'::text) AND ((note)::text ~~ '%(USA)%'::text))", "Rows Removed by Filter": 385584, "Workers": []}, {"Node Type": "Hash", "Parent Relationship": "Inner", "Parallel Aware": false, "Async Capable": false, "Startup Cost": 1.05, "Total Cost": 1.05, "Plan Rows": 1, "Plan Width": 4, "Actual Rows": 1, "Actual Loops": 6, "Hash Buckets": 1024, "Original Hash Buckets": 1024, "Hash Batches": 1, "Original Hash Batches": 1, "Peak Memory Usage": 9, "Workers": [], "Plans": [{"Node Type": "Seq Scan", "Parent Relationship": "Outer", "Parallel Aware": false, "Async Capable": false, "Relation Name": "company_type", "Alias": "ct", "Startup Cost": 0.0, "Total Cost": 1.05, "Plan Rows": 1, "Plan Width": 4, "Actual Rows": 1, "Actual Loops": 6, "Filter": "((kind)::text = 'production companies'::text)", "Rows Removed by Filter": 3, "Workers": []}]}]}]}]}, {"Node Type": "Index Scan", "Parent Relationship": "Inner", "Parallel Aware": false, "Async Capable": false, "Scan Direction": "Forward", "Index Name": "title_pkey", "Relation Name": "title", "Alias": "t", "Startup Cost": 0.43, "Total Cost": 0.71, "Plan Rows": 1, "Plan Width": 21, "Actual Rows": 1, "Actual Loops": 691, "Index Cond": "(id = mi.movie_id)", "Rows Removed by Index Recheck": 0, "Filter": "(production_year > 1990)", "Rows Removed by Filter": 0, "Workers": []}]}]}]}]}, "Planning Time": 6.44, "Triggers": [], "Execution Time": 577.865}, {"Plan": {"Node Type": "Aggregate", "Strategy": "Plain", "Partial Mode": "Finalize", "Parallel Aware": false, "Async Capable": false, "Startup Cost": 264013.4, "Total Cost": 264013.41, "Plan Rows": 1, "Plan Width": 32, "Actual Rows": 1, "Actual Loops": 1, "Plans": [{"Node Type": "Gather", "Parent Relationship": "Outer", "Parallel Aware": false, "Async Capable": false, "Startup Cost": 264012.88, "Total Cost": 264013.39, "Plan Rows": 5, "Plan Width": 32, "Actual Rows": 6, "Actual Loops": 1, "Workers Planned": 5, "Workers Launched": 5, "Single Copy": false, "Plans": [{"Node Type": "Aggregate", "Strategy": "Plain", "Partial Mode": "Partial", "Parent Relationship": "Outer", "Parallel Aware": false, "Async Capable": false, "Startup Cost": 263012.88, "Total Cost": 263012.89, "Plan Rows": 1, "Plan Width": 32, "Actual Rows": 1, "Actual Loops": 6, "Workers": [], "Plans": [{"Node Type": "Nested Loop", "Parent Relationship": "Outer", "Parallel Aware": false, "Async Capable": false, "Join Type": "Inner", "Startup Cost": 32141.49, "Total Cost": 262998.12, "Plan Rows": 5905, "Plan Width": 17, "Actual Rows": 112, "Actual Loops": 6, "Inner Unique": true, "Workers": [], "Plans": [{"Node Type": "Hash Join", "Parent Relationship": "Outer", "Parallel Aware": false, "Async Capable": false, "Join Type": "Inner", "Startup Cost": 32141.06, "Total Cost": 256972.51, "Plan Rows": 8520, "Plan Width": 8, "Actual Rows": 115, "Actual Loops": 6, "Inner Unique": true, "Hash Cond": "(mc.company_type_id = ct.id)", "Workers": [], "Plans": [{"Node Type": "Hash Join", "Parent Relationship": "Outer", "Parallel Aware": false, "Async Capable": false, "Join Type": "Inner", "Startup Cost": 32140.0, "Total Cost": 256787.21, "Plan Rows": 34080, "Plan Width": 12, "Actual Rows": 49154, "Actual Loops": 6, "Inner Unique": true, "Hash Cond": "(mi.info_type_id = it.id)", "Workers": [], "Plans": [{"Node Type": "Hash Join", "Parent Relationship": "Outer", "Parallel Aware": true, "Async Capable": false, "Join Type": "Inner", "Startup Cost": 32136.46, "Total Cost": 247502.14, "Plan Rows": 34080.0, "Plan Width": 16, "Actual Rows": 49154, "Actual Loops": 6, "Inner Unique": false, "Hash Cond": "(mi.movie_id = mc.movie_id)", "Workers": [], "Plans": [{"Node Type": "Seq Scan", "Parent Relationship": "Outer", "Parallel Aware": true, "Async Capable": false, "Relation Name": "movie_info", "Alias": "mi", "Startup Cost": 0.03, "Total Cost": 206156.62, "Plan Rows": 139987, "Plan Width": 8, "Actual Rows": 117779, "Actual Loops": 6, "Filter": "((info)::text = ANY ('{Sweden,Norway,Germany,Denmark,Swedish,Denish,Norwegian,German,USA,American}'::text[]))", "Rows Removed by Filter": 2354841, "Workers": []}, {"Node Type": "Hash", "Parent Relationship": "Inner", "Parallel Aware": true, "Async Capable": false, "Startup Cost": 31448.82, "Total Cost": 31448.82, "Plan Rows": 55009, "Plan Width": 8, "Actual Rows": 49271, "Actual Loops": 6, "Hash Buckets": 524288, "Original Hash Buckets": 262144, "Hash Batches": 1, "Original Hash Batches": 1, "Peak Memory Usage": 17792, "Workers": [], "Plans": [{"Node Type": "Seq Scan", "Parent Relationship": "Outer", "Parallel Aware": true, "Async Capable": false, "Relation Name": "movie_companies", "Alias": "mc", "Startup Cost": 0.0, "Total Cost": 31448.82, "Plan Rows": 55009, "Plan Width": 8, "Actual Rows": 49271, "Actual Loops": 6, "Filter": "(((note)::text !~~ '%(TV)%'::text) AND ((note)::text ~~ '%(USA)%'::text))", "Rows Removed by Filter": 385584, "Workers": []}]}]}, {"Node Type": "Hash", "Parent Relationship": "Inner", "Parallel Aware": false, "Async Capable": false, "Startup Cost": 2.13, "Total Cost": 2.13, "Plan Rows": 113, "Plan Width": 4, "Actual Rows": 113, "Actual Loops": 6, "Hash Buckets": 1024, "Original Hash Buckets": 1024, "Hash Batches": 1, "Original Hash Batches": 1, "Peak Memory Usage": 12, "Workers": [], "Plans": [{"Node Type": "Seq Scan", "Parent Relationship": "Outer", "Parallel Aware": false, "Async Capable": false, "Relation Name": "info_type", "Alias": "it", "Startup Cost": 0.0, "Total Cost": 2.13, "Plan Rows": 113, "Plan Width": 4, "Actual Rows": 113, "Actual Loops": 6, "Workers": []}]}]}, {"Node Type": "Hash", "Parent Relationship": "Inner", "Parallel Aware": false, "Async Capable": false, "Startup Cost": 1.05, "Total Cost": 1.05, "Plan Rows": 1, "Plan Width": 4, "Actual Rows": 1, "Actual Loops": 6, "Hash Buckets": 1024, "Original Hash Buckets": 1024, "Hash Batches": 1, "Original Hash Batches": 1, "Peak Memory Usage": 9, "Workers": [], "Plans": [{"Node Type": "Seq Scan", "Parent Relationship": "Outer", "Parallel Aware": false, "Async Capable": false, "Relation Name": "company_type", "Alias": "ct", "Startup Cost": 0.0, "Total Cost": 1.05, "Plan Rows": 1, "Plan Width": 4, "Actual Rows": 1, "Actual Loops": 6, "Filter": "((kind)::text = 'production companies'::text)", "Rows Removed by Filter": 3, "Workers": []}]}]}, {"Node Type": "Index Scan", "Parent Relationship": "Inner", "Parallel Aware": false, "Async Capable": false, "Scan Direction": "Forward", "Index Name": "title_pkey", "Relation Name": "title", "Alias": "t", "Startup Cost": 0.43, "Total Cost": 0.71, "Plan Rows": 1, "Plan Width": 21, "Actual Rows": 1, "Actual Loops": 691, "Index Cond": "(id = mi.movie_id)", "Rows Removed by Index Recheck": 0, "Filter": "(production_year > 1990)", "Rows Removed by Filter": 0, "Workers": []}]}]}]}]}, "Planning Time": 2.763, "Triggers": [], "Execution Time": 696.999}]